setup.py
defid_notifier/__init__.py
defid_notifier.egg-info/PKG-INFO
defid_notifier.egg-info/SOURCES.txt
defid_notifier.egg-info/dependency_links.txt
defid_notifier.egg-info/entry_points.txt
defid_notifier.egg-info/not-zip-safe
defid_notifier.egg-info/requires.txt
defid_notifier.egg-info/top_level.txt