Metadata-Version: 1.0
Name: defid-notifier
Version: 1.2.6
Summary: Mass notifier for Defacer.ID
Home-page: http://github.com/p4kl0nc4t/defid_notifier
Author: P4kL0nc4t
Author-email: faizzjazadi@gmail.com
License: MIT
Platform: UNKNOWN
